{
  "id": "4d8cb363-8eda-4e72-bede-147c71375c0d",
  "accession_id": "S-BIAD651",
  "name": "Thomas et al source images/Figure 1/Figure 1B/Intestine/Neon--Nup358 XY1664555006_Z00_T0_C1.tif",
  "original_relpath": "Thomas et al source images/Figure 1/Figure 1B/Intestine/Neon--Nup358 XY1664555006_Z00_T0_C1.tif",
  "dimensions": null,
  "representations": [
    {
      "accession_id": "S-BIAD651",
      "image_id": "4d8cb363-8eda-4e72-bede-147c71375c0d",
      "uri": "https://ftp.ebi.ac.uk/biostudies/fire/S-BIAD/651/S-BIAD651/Files/Thomas et al source images/Figure 1/Figure 1B/Intestine/Neon--Nup358 XY1664555006_Z00_T0_C1.tif",
      "size": 44053471,
      "type": "fire_object",
      "dimensions": null,
      "attributes": {
        "fileref_ids": [
          "38e2a4f2-dbac-4b56-b3b2-3f9e06a52653"
        ]
      },
      "rendering": null
    }
  ],
  "attributes": {}
}