{
  "id": "0df6c04c-10ff-496b-8cb3-de674bcf96a9",
  "accession_id": "S-BIAD588",
  "name": "C9K0TU1F - Imported to EMu/NHMUK 010884531 (2).JPG",
  "original_relpath": "C9K0TU1F - Imported to EMu/NHMUK 010884531 (2).JPG",
  "dimensions": null,
  "representations": [
    {
      "accession_id": "S-BIAD588",
      "image_id": "0df6c04c-10ff-496b-8cb3-de674bcf96a9",
      "uri": "https://ftp.ebi.ac.uk/biostudies/fire/S-BIAD/588/S-BIAD588/Files/C9K0TU1F - Imported to EMu/NHMUK 010884531 (2).JPG",
      "size": 6385664,
      "type": "fire_object",
      "dimensions": null,
      "attributes": {
        "fileref_ids": [
          "ff55fe26-b157-4d2b-aa62-ee3db659bb01"
        ]
      },
      "rendering": null
    }
  ],
  "attributes": {
    "NHMUK barcode": "010884531",
    "Project name": null,
    "Preservation": null,
    "Date of Collection": "30/06/2022",
    "Location": "Bure Marshes NNR, Norfolk, England, United Kingdom, 52 41 33 N, 1 27 34 E, Europe",
    "Phylum": null,
    "Class": null,
    "Order": "Hymenoptera",
    "Family": null,
    "Genus": null,
    "Species": null,
    "Scientific Name": "Aleiodes circumscriptus (Nees, 1834)",
    "Collector": "Dr David C. Lees; Natural History Museum; Entomology; Lees",
    "Identifier": "Dr Gavin R. Broad",
    "Site Decimal Latitude": "52.6925",
    "Site Decimal Longitude": "1.4594"
  }
}