{
  "id": "3ce0fb42-0257-4e55-b07d-796733c2b16a",
  "accession_id": "S-BIAD588",
  "name": "C9K02U9Z and C9X0CNI7 - Imported to EMu/014439763 (3).JPG",
  "original_relpath": "C9K02U9Z and C9X0CNI7 - Imported to EMu/014439763 (3).JPG",
  "dimensions": null,
  "representations": [
    {
      "accession_id": "S-BIAD588",
      "image_id": "3ce0fb42-0257-4e55-b07d-796733c2b16a",
      "uri": "https://ftp.ebi.ac.uk/biostudies/fire/S-BIAD/588/S-BIAD588/Files/C9K02U9Z and C9X0CNI7 - Imported to EMu/014439763 (3).JPG",
      "size": 5541376,
      "type": "fire_object",
      "dimensions": null,
      "attributes": {
        "fileref_ids": [
          "5dd3e5b2-6ead-4e24-9c03-9e5912a61b6c"
        ]
      },
      "rendering": null
    }
  ],
  "attributes": {
    "NHMUK barcode": "014439763",
    "Project name": "Darwin Tree of Life",
    "Preservation": "Dry frozen (-80°C)",
    "Date of Collection": "8/3/2021",
    "Location": "Nearest Named Place: Chelsea Harbour, England, United Kingdom, 51 28  N, 0 11  W, Europe",
    "Phylum": "Arthropoda",
    "Class": "Insecta",
    "Order": "Coleoptera",
    "Family": "Curculionidae",
    "Genus": "Otiorhynchus",
    "Species": "armadillo",
    "Scientific Name": "Otiorhynchus armadillo",
    "Collector": "Maxwell V.L. Barclay; Natural History Museum; Department of Entomology; Barclay",
    "Identifier": "Maxwell V.L. Barclay",
    "Site Decimal Latitude": null,
    "Site Decimal Longitude": null
  }
}