{
  "id": "4d02c306-e09c-4556-9616-56b4d844c0b7",
  "accession_id": "S-BIAD588",
  "name": "C9K02TWV - Imported to EMu/014036929_2.JPG",
  "original_relpath": "C9K02TWV - Imported to EMu/014036929_2.JPG",
  "dimensions": null,
  "representations": [
    {
      "accession_id": "S-BIAD588",
      "image_id": "4d02c306-e09c-4556-9616-56b4d844c0b7",
      "uri": "https://ftp.ebi.ac.uk/biostudies/fire/S-BIAD/588/S-BIAD588/Files/C9K02TWV - Imported to EMu/014036929_2.JPG",
      "size": 5992960,
      "type": "fire_object",
      "dimensions": null,
      "attributes": {
        "fileref_ids": [
          "8ea126b5-1f71-4c33-9fd8-e662b151c3fa"
        ]
      },
      "rendering": null
    }
  ],
  "attributes": {
    "NHMUK barcode": "014036929",
    "Project name": "Darwin Tree of Life",
    "Preservation": "Dry frozen (-80°C)",
    "Date of Collection": "6/28/2021",
    "Location": "Lizard Point, S W Coast Path, Lizard, Helston TR12 7NT, United Kingdom, 49 57 34.176 N, 5 12 20.658 W, Europe",
    "Phylum": "Arthropoda",
    "Class": "Insecta",
    "Order": "Diptera",
    "Family": "Rhagionidae",
    "Genus": "Rhagio",
    "Species": "scolopacea",
    "Scientific Name": "Rhagio scolopacea",
    "Collector": "Dr. Mike Ashworth; University of Manchester;  study of British Diptera; Ashworth",
    "Identifier": "Dr. Mike Ashworth",
    "Site Decimal Latitude": null,
    "Site Decimal Longitude": null
  }
}