{
  "id": "7451b957-7204-4a30-a4ce-d18c57a49e4b",
  "accession_id": "S-BIAD588",
  "name": "C9K02TWV - Imported to EMu/014438385_3.JPG",
  "original_relpath": "C9K02TWV - Imported to EMu/014438385_3.JPG",
  "dimensions": null,
  "representations": [
    {
      "accession_id": "S-BIAD588",
      "image_id": "7451b957-7204-4a30-a4ce-d18c57a49e4b",
      "uri": "https://ftp.ebi.ac.uk/biostudies/fire/S-BIAD/588/S-BIAD588/Files/C9K02TWV - Imported to EMu/014438385_3.JPG",
      "size": 4028416,
      "type": "fire_object",
      "dimensions": null,
      "attributes": {
        "fileref_ids": [
          "70900654-f8d1-4626-94a4-445dba00288e"
        ]
      },
      "rendering": null
    }
  ],
  "attributes": {
    "NHMUK barcode": "014438385",
    "Project name": null,
    "Preservation": null,
    "Date of Collection": null,
    "Location": null,
    "Phylum": null,
    "Class": null,
    "Order": null,
    "Family": null,
    "Genus": null,
    "Species": null,
    "Scientific Name": null,
    "Collector": null,
    "Identifier": null,
    "Site Decimal Latitude": null,
    "Site Decimal Longitude": null
  }
}