{
  "id": "a1c86685-becd-40b1-bfcd-923da362aca9",
  "accession_id": "S-BIAD588",
  "name": "C9N04OWA - Imported to EMu/NHMUK014444897-02.JPG",
  "original_relpath": "C9N04OWA - Imported to EMu/NHMUK014444897-02.JPG",
  "dimensions": null,
  "representations": [
    {
      "accession_id": "S-BIAD588",
      "image_id": "a1c86685-becd-40b1-bfcd-923da362aca9",
      "uri": "https://ftp.ebi.ac.uk/biostudies/fire/S-BIAD/588/S-BIAD588/Files/C9N04OWA - Imported to EMu/NHMUK014444897-02.JPG",
      "size": 5445120,
      "type": "fire_object",
      "dimensions": null,
      "attributes": {
        "fileref_ids": [
          "d451a3a9-4912-4658-971e-310b827f400b"
        ]
      },
      "rendering": null
    }
  ],
  "attributes": {
    "NHMUK barcode": "014444897",
    "Project name": null,
    "Preservation": null,
    "Date of Collection": "18/10/2020",
    "Location": "Wigmore park, Luton, United Kingdom, Europe",
    "Phylum": null,
    "Class": null,
    "Order": "Araneae",
    "Family": null,
    "Genus": null,
    "Species": null,
    "Scientific Name": "Tetragnatha extensa (Linnaeus, 1758)",
    "Collector": "Olga Sivell; Natural History Museum; Life Sciences; Sivell_x000D_. Sergio Henriques; Henriques",
    "Identifier": "Sergio Henriques",
    "Site Decimal Latitude": null,
    "Site Decimal Longitude": null
  }
}