{
  "id": "b6f91511-dea4-46ab-b970-73916f2dd856",
  "accession_id": "S-BIAD588",
  "name": "C9K02UD9 - Imported to EMu/NHMUK 014433266 (1).JPG",
  "original_relpath": "C9K02UD9 - Imported to EMu/NHMUK 014433266 (1).JPG",
  "dimensions": null,
  "representations": [
    {
      "accession_id": "S-BIAD588",
      "image_id": "b6f91511-dea4-46ab-b970-73916f2dd856",
      "uri": "https://ftp.ebi.ac.uk/biostudies/fire/S-BIAD/588/S-BIAD588/Files/C9K02UD9 - Imported to EMu/NHMUK 014433266 (1).JPG",
      "size": 6873600,
      "type": "fire_object",
      "dimensions": null,
      "attributes": {
        "fileref_ids": [
          "e66a9ea8-419a-4cb4-a992-bbba74568730"
        ]
      },
      "rendering": null
    }
  ],
  "attributes": {
    "NHMUK barcode": "014433266",
    "Project name": null,
    "Preservation": null,
    "Date of Collection": "22/05/2021",
    "Location": "Fulmead Street, Parsons Green, London, England, United Kingdom, 51 28  N, 0 11  W, Europe",
    "Phylum": null,
    "Class": null,
    "Order": "Hymenoptera",
    "Family": null,
    "Genus": null,
    "Species": null,
    "Scientific Name": "Cleonymus obscurus Walker, 1837",
    "Collector": "Maxwell V.L. Barclay; Natural History Museum; Department of Entomology; Barclay",
    "Identifier": "Maxwell V.L. Barclay",
    "Site Decimal Latitude": "51.47",
    "Site Decimal Longitude": "-0.18"
  }
}