{
  "id": "b912665a-a465-456c-8fab-a528e84b6e84",
  "accession_id": "S-BIAD588",
  "name": "C9K02U1C - Imported to EMu/014042305_3.JPG",
  "original_relpath": "C9K02U1C - Imported to EMu/014042305_3.JPG",
  "dimensions": null,
  "representations": [
    {
      "accession_id": "S-BIAD588",
      "image_id": "b912665a-a465-456c-8fab-a528e84b6e84",
      "uri": "https://ftp.ebi.ac.uk/biostudies/fire/S-BIAD/588/S-BIAD588/Files/C9K02U1C - Imported to EMu/014042305_3.JPG",
      "size": 3564032,
      "type": "fire_object",
      "dimensions": null,
      "attributes": {
        "fileref_ids": [
          "2b18ce4d-90a9-4761-b890-760bac6346b5"
        ]
      },
      "rendering": null
    }
  ],
  "attributes": {
    "NHMUK barcode": "014042305",
    "Project name": null,
    "Preservation": null,
    "Date of Collection": null,
    "Location": null,
    "Phylum": null,
    "Class": null,
    "Order": null,
    "Family": null,
    "Genus": null,
    "Species": null,
    "Scientific Name": null,
    "Collector": null,
    "Identifier": null,
    "Site Decimal Latitude": null,
    "Site Decimal Longitude": null
  }
}