{
  "id": "c63435b0-ba16-4e99-be61-fe2b48eea6dc",
  "accession_id": "S-BIAD588",
  "name": "C9N04OWA - Imported to EMu/NHMUK014449097-10.JPG",
  "original_relpath": "C9N04OWA - Imported to EMu/NHMUK014449097-10.JPG",
  "dimensions": null,
  "representations": [
    {
      "accession_id": "S-BIAD588",
      "image_id": "c63435b0-ba16-4e99-be61-fe2b48eea6dc",
      "uri": "https://ftp.ebi.ac.uk/biostudies/fire/S-BIAD/588/S-BIAD588/Files/C9N04OWA - Imported to EMu/NHMUK014449097-10.JPG",
      "size": 5408768,
      "type": "fire_object",
      "dimensions": null,
      "attributes": {
        "fileref_ids": [
          "cafe2702-bc65-42d9-9551-3bee72bc9c3e"
        ]
      },
      "rendering": null
    }
  ],
  "attributes": {
    "NHMUK barcode": "014449097",
    "Project name": null,
    "Preservation": null,
    "Date of Collection": "16/10/2020",
    "Location": "London Zoo (Indoors, on the wall of the office building), London, England, United Kingdom, 51 32 6.83 N, 0 9 20.51 W, Europe",
    "Phylum": null,
    "Class": null,
    "Order": "Araneae",
    "Family": null,
    "Genus": null,
    "Species": null,
    "Scientific Name": "Oecobius navus Blackwall, 1859",
    "Collector": "Sergio Henriques; Henriques",
    "Identifier": "Sergio Henriques",
    "Site Decimal Latitude": "51.535231",
    "Site Decimal Longitude": "-0.155698"
  }
}