{
  "id": "c6fc1c86-f4ac-4e4b-ad0a-4d268d46dd9a",
  "accession_id": "S-BIAD588",
  "name": "C9K02UD9 - Imported to EMu/NHMUK 013805982 (1).JPG",
  "original_relpath": "C9K02UD9 - Imported to EMu/NHMUK 013805982 (1).JPG",
  "dimensions": null,
  "representations": [
    {
      "accession_id": "S-BIAD588",
      "image_id": "c6fc1c86-f4ac-4e4b-ad0a-4d268d46dd9a",
      "uri": "https://ftp.ebi.ac.uk/biostudies/fire/S-BIAD/588/S-BIAD588/Files/C9K02UD9 - Imported to EMu/NHMUK 013805982 (1).JPG",
      "size": 6453248,
      "type": "fire_object",
      "dimensions": null,
      "attributes": {
        "fileref_ids": [
          "b86e31f3-2de4-492c-96f8-84b57c901064"
        ]
      },
      "rendering": null
    }
  ],
  "attributes": {
    "NHMUK barcode": "013805982",
    "Project name": null,
    "Preservation": null,
    "Date of Collection": "29/07/2021",
    "Location": "Hartslock NR, England, United Kingdom, 51 30 42.47 N, 1 6 48.932 W, Europe",
    "Phylum": null,
    "Class": null,
    "Order": "Coleoptera",
    "Family": null,
    "Genus": null,
    "Species": null,
    "Scientific Name": "Sermylassa halensis (Linnaeus, 1767)",
    "Collector": "Dr Ian Sims; The British Entomological and Natural History Society (BENHS); Sims",
    "Identifier": "Dr Michael F. Geiser",
    "Site Decimal Latitude": "51.511797",
    "Site Decimal Longitude": "-1.1135922"
  }
}