{
  "id": "d2daa0f2-77f7-4f90-a7dc-6ea89f4ac19b",
  "accession_id": "S-BIAD588",
  "name": "C9N04OWA - Imported to EMu/NHMUK014449144-02.JPG",
  "original_relpath": "C9N04OWA - Imported to EMu/NHMUK014449144-02.JPG",
  "dimensions": null,
  "representations": [
    {
      "accession_id": "S-BIAD588",
      "image_id": "d2daa0f2-77f7-4f90-a7dc-6ea89f4ac19b",
      "uri": "https://ftp.ebi.ac.uk/biostudies/fire/S-BIAD/588/S-BIAD588/Files/C9N04OWA - Imported to EMu/NHMUK014449144-02.JPG",
      "size": 5552640,
      "type": "fire_object",
      "dimensions": null,
      "attributes": {
        "fileref_ids": [
          "03a0f04e-097d-4166-b084-abcc8b520c52"
        ]
      },
      "rendering": null
    }
  ],
  "attributes": {
    "NHMUK barcode": "014449144",
    "Project name": null,
    "Preservation": null,
    "Date of Collection": "22/10/2020",
    "Location": "Dean's Garden Centre, Stockton on the Forest, York, England, United Kingdom, 53 59 20 N, 1 0 53 W, Europe",
    "Phylum": null,
    "Class": null,
    "Order": "Araneae",
    "Family": null,
    "Genus": null,
    "Species": null,
    "Scientific Name": "Uloborus plumipes Lucas, 1846",
    "Collector": "Dr Geoff Oxford; University of York; Oxford",
    "Identifier": "Dr Geoff Oxford",
    "Site Decimal Latitude": "53.9888",
    "Site Decimal Longitude": "-1.0147"
  }
}