{
  "id": "f58a4421-f1bc-40c7-83ae-69bfff10b718",
  "accession_id": "S-BIAD588",
  "name": "C9K02U9Z and C9X0CNI7 - Imported to EMu/014551978_dorsal.JPG",
  "original_relpath": "C9K02U9Z and C9X0CNI7 - Imported to EMu/014551978_dorsal.JPG",
  "dimensions": null,
  "representations": [
    {
      "accession_id": "S-BIAD588",
      "image_id": "f58a4421-f1bc-40c7-83ae-69bfff10b718",
      "uri": "https://ftp.ebi.ac.uk/biostudies/fire/S-BIAD/588/S-BIAD588/Files/C9K02U9Z and C9X0CNI7 - Imported to EMu/014551978_dorsal.JPG",
      "size": 5382656,
      "type": "fire_object",
      "dimensions": null,
      "attributes": {
        "fileref_ids": [
          "f0608315-3d47-4f0d-915b-6eafd34cde28"
        ]
      },
      "rendering": null
    }
  ],
  "attributes": {
    "NHMUK barcode": "014551978",
    "Project name": "Darwin Tree of Life",
    "Preservation": "Ethanol",
    "Date of Collection": "8/22/2021",
    "Location": "Burnham Beeches, United Kingdom",
    "Phylum": "Arthropoda",
    "Class": "Diplopoda",
    "Order": null,
    "Family": "Blaniulidae",
    "Genus": "Proteroiulus",
    "Species": "fuscus",
    "Scientific Name": "Proteroiulus fuscus",
    "Collector": "Ms Helen Reid; Reid",
    "Identifier": "Ms Helen Reid",
    "Site Decimal Latitude": null,
    "Site Decimal Longitude": null
  }
}