{
  "id": "148371f2-80b9-49fb-9897-b000f34afa77",
  "accession_id": "S-BIAD885",
  "name": "idr0010/14-35.ome.zarr.zip",
  "original_relpath": "idr0010/14-35.ome.zarr.zip",
  "dimensions": null,
  "representations": [
    {
      "accession_id": "S-BIAD885",
      "image_id": "148371f2-80b9-49fb-9897-b000f34afa77",
      "uri": "https://ftp.ebi.ac.uk/biostudies/fire/S-BIAD/885/S-BIAD885/Files/idr0010/14-35.ome.zarr.zip",
      "size": 462685553,
      "type": "zipped_zarr",
      "dimensions": null,
      "attributes": {
        "fileref_ids": [
          "17e591ff-9bcf-4906-9fb8-30edeb4d28f1"
        ],
        "path_in_zarr": "/0"
      },
      "rendering": null
    }
  ],
  "attributes": {}
}