{
  "id": "442aa2e9-ac35-4834-af88-aec9518a48c9",
  "accession_id": "S-BIAD624",
  "name": "Source data for microscopy images/Figure 2/2D/Image for A549 TT-Ki67 positive cancer cells.tif",
  "original_relpath": "Source data for microscopy images/Figure 2/2D/Image for A549 TT-Ki67 positive cancer cells.tif",
  "dimensions": null,
  "representations": [
    {
      "accession_id": "S-BIAD624",
      "image_id": "442aa2e9-ac35-4834-af88-aec9518a48c9",
      "uri": "https://ftp.ebi.ac.uk/biostudies/fire/S-BIAD/624/S-BIAD624/Files/Source data for microscopy images/Figure 2/2D/Image for A549 TT-Ki67 positive cancer cells.tif",
      "size": 37635276,
      "type": "fire_object",
      "dimensions": null,
      "attributes": {
        "fileref_ids": [
          "48a0855e-4a50-4973-aed8-cc06540aeeea"
        ]
      },
      "rendering": null
    }
  ],
  "attributes": {
    "Microscope type": "Optical microscope",
    "Specimen species": "Mouse",
    "Specimen type": "subcutaneous tumor section"
  }
}