{
  "id": "e3286f6d-6f85-4075-95dd-858020e2dd05",
  "accession_id": "S-BIAD624",
  "name": "Source data for microscopy images/Figure 1/1I/Image for H460 TT-migration.tif",
  "original_relpath": "Source data for microscopy images/Figure 1/1I/Image for H460 TT-migration.tif",
  "dimensions": null,
  "representations": [
    {
      "accession_id": "S-BIAD624",
      "image_id": "e3286f6d-6f85-4075-95dd-858020e2dd05",
      "uri": "https://ftp.ebi.ac.uk/biostudies/fire/S-BIAD/624/S-BIAD624/Files/Source data for microscopy images/Figure 1/1I/Image for H460 TT-migration.tif",
      "size": 4211428,
      "type": "fire_object",
      "dimensions": null,
      "attributes": {
        "fileref_ids": [
          "bb67e39d-a57f-4fbc-9e14-2013289589c8"
        ]
      },
      "rendering": null
    }
  ],
  "attributes": {
    "Microscope type": "Optical microscope",
    "Specimen species": "Human",
    "Specimen type": "lung cancer cell"
  }
}