{
  "id": "83be998b-1a75-40e8-8a3e-40c0da666402",
  "accession_id": "S-BIAD562",
  "name": "trrWT_25C/Image029.tif",
  "original_relpath": "trrWT_25C/Image029.tif",
  "dimensions": null,
  "representations": [
    {
      "accession_id": "S-BIAD562",
      "image_id": "83be998b-1a75-40e8-8a3e-40c0da666402",
      "uri": "https://ftp.ebi.ac.uk/biostudies/fire/S-BIAD/562/S-BIAD562/Files/H3K4me1_robustness/Reaction_norms/trrWT_25C.zip",
      "size": 12006292,
      "type": "fire_object",
      "dimensions": null,
      "attributes": {
        "fileref_ids": [
          "d15183c2-ca09-495c-bf52-189c8fe863a2"
        ]
      },
      "rendering": null
    }
  ],
  "attributes": {}
}