{
  "id": "db60e2af-c60e-497b-9857-618ff09797ef",
  "accession_id": "S-BIAD562",
  "name": "trrCA_25C/Image161.tif",
  "original_relpath": "trrCA_25C/Image161.tif",
  "dimensions": null,
  "representations": [
    {
      "accession_id": "S-BIAD562",
      "image_id": "db60e2af-c60e-497b-9857-618ff09797ef",
      "uri": "https://ftp.ebi.ac.uk/biostudies/fire/S-BIAD/562/S-BIAD562/Files/H3K4me1_robustness/Reaction_norms/trrCA_25C.zip",
      "size": 12006292,
      "type": "fire_object",
      "dimensions": null,
      "attributes": {
        "fileref_ids": [
          "92a8b655-7e0c-4aa9-ae84-73d74d4b98d2"
        ]
      },
      "rendering": null
    }
  ],
  "attributes": {}
}