{
  "id": "e70ed681-c3b0-4dee-a1b2-1f924c4d38da",
  "accession_id": "S-BIAD562",
  "name": "trrWT_29C/Image053.tif",
  "original_relpath": "trrWT_29C/Image053.tif",
  "dimensions": null,
  "representations": [
    {
      "accession_id": "S-BIAD562",
      "image_id": "e70ed681-c3b0-4dee-a1b2-1f924c4d38da",
      "uri": "https://ftp.ebi.ac.uk/biostudies/fire/S-BIAD/562/S-BIAD562/Files/H3K4me1_robustness/Reaction_norms/trrWT_29C.zip",
      "size": 12006292,
      "type": "fire_object",
      "dimensions": null,
      "attributes": {
        "fileref_ids": [
          "b4ad624b-7cf4-4a18-8744-dcc5da9e7e05"
        ]
      },
      "rendering": null
    }
  ],
  "attributes": {}
}