{
  "id": "333f7043-87e6-41a0-8348-b19ffffef217",
  "accession_id": "S-BIAD629",
  "name": "STRIP/CE_LAA/CE_211.svs",
  "original_relpath": "STRIP/CE_LAA/CE_211.svs",
  "dimensions": null,
  "representations": [
    {
      "accession_id": "S-BIAD629",
      "image_id": "333f7043-87e6-41a0-8348-b19ffffef217",
      "uri": "https://ftp.ebi.ac.uk/biostudies/fire/S-BIAD/629/S-BIAD629/Files/STRIP/CE_LAA/CE_211.svs",
      "size": 226781453,
      "type": "fire_object",
      "dimensions": null,
      "attributes": {
        "fileref_ids": [
          "aa4931bf-a406-4b87-80e4-6a44874fe3d7"
        ]
      },
      "rendering": null
    }
  ],
  "attributes": {
    "center_ID": "5",
    "slide_id": "CE_211",
    "case_id": "CE_211",
    "Origin_Label": "CE"
  }
}