{
  "id": "4a4fd838-63d1-4ccd-a7fb-59708d1d08e4",
  "accession_id": "S-BIAD629",
  "name": "STRIP/Unknown/Unknown_291_1.svs",
  "original_relpath": "STRIP/Unknown/Unknown_291_1.svs",
  "dimensions": null,
  "representations": [
    {
      "accession_id": "S-BIAD629",
      "image_id": "4a4fd838-63d1-4ccd-a7fb-59708d1d08e4",
      "uri": "https://ftp.ebi.ac.uk/biostudies/fire/S-BIAD/629/S-BIAD629/Files/STRIP/Unknown/Unknown_291_1.svs",
      "size": 262771747,
      "type": "fire_object",
      "dimensions": null,
      "attributes": {
        "fileref_ids": [
          "4674f81a-2ccc-46ad-b698-8e30565fabd9"
        ]
      },
      "rendering": null
    }
  ],
  "attributes": {
    "center_ID": null,
    "slide_id": "Unknown_291_1",
    "case_id": "Unknown_291",
    "Origin_Label": "Unknown"
  }
}