{
  "id": "4d0c2e2c-ca89-4857-8ab4-00953af6aee8",
  "accession_id": "S-BIAD629",
  "name": "STRIP/Unknown/Unknown_163.svs",
  "original_relpath": "STRIP/Unknown/Unknown_163.svs",
  "dimensions": null,
  "representations": [
    {
      "accession_id": "S-BIAD629",
      "image_id": "4d0c2e2c-ca89-4857-8ab4-00953af6aee8",
      "uri": "https://ftp.ebi.ac.uk/biostudies/fire/S-BIAD/629/S-BIAD629/Files/STRIP/Unknown/Unknown_163.svs",
      "size": 12542083,
      "type": "fire_object",
      "dimensions": null,
      "attributes": {
        "fileref_ids": [
          "93b73168-ff16-4334-8888-4a9f982bbc14"
        ]
      },
      "rendering": null
    }
  ],
  "attributes": {
    "center_ID": null,
    "slide_id": "Unknown_163",
    "case_id": "Unknown_163",
    "Origin_Label": "Unknown"
  }
}