{
  "id": "6f951514-bdae-4259-abd6-5cf7caea9e8f",
  "accession_id": "S-BIAD629",
  "name": "STRIP/CE_LAA/CE_39.svs",
  "original_relpath": "STRIP/CE_LAA/CE_39.svs",
  "dimensions": null,
  "representations": [
    {
      "accession_id": "S-BIAD629",
      "image_id": "6f951514-bdae-4259-abd6-5cf7caea9e8f",
      "uri": "https://ftp.ebi.ac.uk/biostudies/fire/S-BIAD/629/S-BIAD629/Files/STRIP/CE_LAA/CE_39.svs",
      "size": 130833985,
      "type": "fire_object",
      "dimensions": null,
      "attributes": {
        "fileref_ids": [
          "a656b980-1a98-46d5-94c1-5349e4b3503b"
        ]
      },
      "rendering": null
    }
  ],
  "attributes": {
    "center_ID": "1",
    "slide_id": "CE_39",
    "case_id": "CE_39",
    "Origin_Label": "CE"
  }
}