{
  "id": "a72cc9ed-45f5-45cf-a017-f9b90fd2cf6c",
  "accession_id": "S-BIAD629",
  "name": "STRIP/Unknown/Unknown_178_1.svs",
  "original_relpath": "STRIP/Unknown/Unknown_178_1.svs",
  "dimensions": null,
  "representations": [
    {
      "accession_id": "S-BIAD629",
      "image_id": "a72cc9ed-45f5-45cf-a017-f9b90fd2cf6c",
      "uri": "https://ftp.ebi.ac.uk/biostudies/fire/S-BIAD/629/S-BIAD629/Files/STRIP/Unknown/Unknown_178_1.svs",
      "size": 24920371,
      "type": "fire_object",
      "dimensions": null,
      "attributes": {
        "fileref_ids": [
          "6dd3063d-83c7-4c83-9ce6-36cee57a256e"
        ]
      },
      "rendering": null
    }
  ],
  "attributes": {
    "center_ID": null,
    "slide_id": "Unknown_178_1",
    "case_id": "Unknown_178",
    "Origin_Label": "Unknown"
  }
}