{
  "id": "b0569910-516f-4f09-b292-30bb735f2bac",
  "accession_id": "S-BIAD629",
  "name": "STRIP/Unknown/Unknown_166.svs",
  "original_relpath": "STRIP/Unknown/Unknown_166.svs",
  "dimensions": null,
  "representations": [
    {
      "accession_id": "S-BIAD629",
      "image_id": "b0569910-516f-4f09-b292-30bb735f2bac",
      "uri": "https://ftp.ebi.ac.uk/biostudies/fire/S-BIAD/629/S-BIAD629/Files/STRIP/Unknown/Unknown_166.svs",
      "size": 187370145,
      "type": "fire_object",
      "dimensions": null,
      "attributes": {
        "fileref_ids": [
          "178f2301-5130-4423-9fbc-c5d1301ff040"
        ]
      },
      "rendering": null
    }
  ],
  "attributes": {
    "center_ID": null,
    "slide_id": "Unknown_166",
    "case_id": "Unknown_166",
    "Origin_Label": "Unknown"
  }
}