{
  "id": "e644bcc1-70b3-4cee-8754-ed9746646492",
  "accession_id": "S-BIAD629",
  "name": "STRIP/Unknown/Unknown_224.svs",
  "original_relpath": "STRIP/Unknown/Unknown_224.svs",
  "dimensions": null,
  "representations": [
    {
      "accession_id": "S-BIAD629",
      "image_id": "e644bcc1-70b3-4cee-8754-ed9746646492",
      "uri": "https://ftp.ebi.ac.uk/biostudies/fire/S-BIAD/629/S-BIAD629/Files/STRIP/Unknown/Unknown_224.svs",
      "size": 74374801,
      "type": "fire_object",
      "dimensions": null,
      "attributes": {
        "fileref_ids": [
          "5dfe496b-076c-4f41-99bf-5eab1a133c94"
        ]
      },
      "rendering": null
    }
  ],
  "attributes": {
    "center_ID": null,
    "slide_id": "Unknown_224",
    "case_id": "Unknown_224",
    "Origin_Label": "Unknown"
  }
}