{
  "id": "f910cc11-8a46-438f-a7e8-18403971064a",
  "accession_id": "S-BSST1009",
  "name": "M nAN_IN_3_143.czi",
  "original_relpath": "M nAN_IN_3_143.czi",
  "dimensions": null,
  "representations": [
    {
      "accession_id": "S-BSST1009",
      "image_id": "f910cc11-8a46-438f-a7e8-18403971064a",
      "uri": "https://ftp.ebi.ac.uk/biostudies/fire/S-BSST/009/S-BSST1009/Files/All together adult VGLUT2.zip",
      "size": 1129203808,
      "type": "fire_object",
      "dimensions": null,
      "attributes": {
        "fileref_ids": [
          "f77ceccd-725a-4a2d-b20e-1ae80b97d1ae"
        ]
      },
      "rendering": null
    }
  ],
  "attributes": {
    "Description": "VGLUT2 Raw images used for Fig. 4-6",
    "Type": "CZI files (confocal images)"
  }
}