{
  "id": "093b521f-301b-4355-8fc8-46253d3593a7",
  "accession_id": "S-BIAD633",
  "name": "Timecourses/Individual_cells/Sequence_ TC05 T0 008-MaxIP.nd2_crop1 - 124 x 122 x 1 x 1 - 2 ch (double).tif",
  "original_relpath": "Timecourses/Individual_cells/Sequence_ TC05 T0 008-MaxIP.nd2_crop1 - 124 x 122 x 1 x 1 - 2 ch (double).tif",
  "dimensions": null,
  "representations": [
    {
      "accession_id": "S-BIAD633",
      "image_id": "093b521f-301b-4355-8fc8-46253d3593a7",
      "uri": "https://ftp.ebi.ac.uk/biostudies/fire/S-BIAD/633/S-BIAD633/Files/Timecourses/Individual_cells/Sequence_ TC05 T0 008-MaxIP.nd2_crop1 - 124 x 122 x 1 x 1 - 2 ch (double).tif",
      "size": 115561,
      "type": "fire_object",
      "dimensions": null,
      "attributes": {
        "fileref_ids": [
          "93e98cfd-1c36-48d1-a699-58cc9a568ab0"
        ]
      },
      "rendering": null
    }
  ],
  "attributes": {
    "Filetype": "ICY_ROI",
    "Experiment ID": "TIME_02_05_23",
    "Assay Type": "Gametogenesis_timecourse",
    "Sample type": "Experimental",
    "Time treated post induction (min)": "0",
    "Compound identifier": "TC05",
    "TCAMS identifier": "TCMDC-137984",
    "ChEMBL identifier": "CHEMBL528003",
    "Compound linkout": "https://www.ebi.ac.uk/chembl/compound_report_card/CHEMBL528003/",
    "Concentration (uM)": "2"
  }
}