{
  "id": "1b446c06-e197-49ab-aca9-b365327e751c",
  "accession_id": "S-BIAD633",
  "name": "Timecourses/Individual_cells/Sequence_ 221019 ML10 T02 010 - Deconvolved, Type Automatic-MaxIP.nd2_crop4 - 105 x 186 x 1 x 1 - 2 ch (double).tif",
  "original_relpath": "Timecourses/Individual_cells/Sequence_ 221019 ML10 T02 010 - Deconvolved, Type Automatic-MaxIP.nd2_crop4 - 105 x 186 x 1 x 1 - 2 ch (double).tif",
  "dimensions": null,
  "representations": [
    {
      "accession_id": "S-BIAD633",
      "image_id": "1b446c06-e197-49ab-aca9-b365327e751c",
      "uri": "https://ftp.ebi.ac.uk/biostudies/fire/S-BIAD/633/S-BIAD633/Files/Timecourses/Individual_cells/Sequence_ 221019 ML10 T02 010 - Deconvolved, Type Automatic-MaxIP.nd2_crop4 - 105 x 186 x 1 x 1 - 2 ch (double).tif",
      "size": 155407,
      "type": "fire_object",
      "dimensions": null,
      "attributes": {
        "fileref_ids": [
          "c7aa32ce-add5-40da-8161-bc82d433bf8b"
        ]
      },
      "rendering": null
    }
  ],
  "attributes": {
    "Filetype": "ISOLATED_CELL",
    "Experiment ID": "TIME_ML10_04_13_41",
    "Assay Type": "Gametogenesis_timecourse",
    "Sample type": "Experimental",
    "Time treated post induction (min)": "2",
    "Compound identifier": "ML10",
    "TCAMS identifier": "NA",
    "ChEMBL identifier": "NA",
    "Compound linkout": "NA",
    "Concentration (uM)": "1"
  }
}