{
  "id": "70180ac2-2618-4c02-9b38-9d65c9cb8475",
  "accession_id": "S-BIAD633",
  "name": "Timecourses/Individual_cells/Sequence_ TC05 T10 006-MaxIP.nd2_crop3 - 147 x 130 x 1 x 1 - 2 ch (double).tif",
  "original_relpath": "Timecourses/Individual_cells/Sequence_ TC05 T10 006-MaxIP.nd2_crop3 - 147 x 130 x 1 x 1 - 2 ch (double).tif",
  "dimensions": null,
  "representations": [
    {
      "accession_id": "S-BIAD633",
      "image_id": "70180ac2-2618-4c02-9b38-9d65c9cb8475",
      "uri": "https://ftp.ebi.ac.uk/biostudies/fire/S-BIAD/633/S-BIAD633/Files/Timecourses/Individual_cells/Sequence_ TC05 T10 006-MaxIP.nd2_crop3 - 147 x 130 x 1 x 1 - 2 ch (double).tif",
      "size": 138100,
      "type": "fire_object",
      "dimensions": null,
      "attributes": {
        "fileref_ids": [
          "35e24143-1bf5-43af-b735-6398c55dec1b"
        ]
      },
      "rendering": null
    }
  ],
  "attributes": {
    "Filetype": "ICY_ROI",
    "Experiment ID": "TIME_02_05_23",
    "Assay Type": "Gametogenesis_timecourse",
    "Sample type": "Experimental",
    "Time treated post induction (min)": "10",
    "Compound identifier": "TC05",
    "TCAMS identifier": "TCMDC-137984",
    "ChEMBL identifier": "CHEMBL528003",
    "Compound linkout": "https://www.ebi.ac.uk/chembl/compound_report_card/CHEMBL528003/",
    "Concentration (uM)": "2"
  }
}