{
  "id": "9c267e4d-d79d-4ff8-b2fd-5535e2ec31cb",
  "accession_id": "S-BIAD633",
  "name": "Timecourses/Masked/Sequence_ TCMDC-123880 t05 15.nd2 (channels 0 1) - 2560 x 2160 x 1 x 1 - 2 ch (double).tif",
  "original_relpath": "Timecourses/Masked/Sequence_ TCMDC-123880 t05 15.nd2 (channels 0 1) - 2560 x 2160 x 1 x 1 - 2 ch (double).tif",
  "dimensions": null,
  "representations": [
    {
      "accession_id": "S-BIAD633",
      "image_id": "9c267e4d-d79d-4ff8-b2fd-5535e2ec31cb",
      "uri": "https://ftp.ebi.ac.uk/biostudies/fire/S-BIAD/633/S-BIAD633/Files/Timecourses/Masked/Sequence_ TCMDC-123880 t05 15.nd2 (channels 0 1) - 2560 x 2160 x 1 x 1 - 2 ch (double).tif",
      "size": 24955983,
      "type": "fire_object",
      "dimensions": null,
      "attributes": {
        "fileref_ids": [
          "1fa1b58f-7d2d-4a94-8e58-52d87e2a5eec"
        ]
      },
      "rendering": null
    }
  ],
  "attributes": {
    "Filetype": "BACK_COR_Image",
    "Experiment ID": "TIME_VB_39",
    "Assay Type": "Gametogenesis_timecourse",
    "Sample type": "Experimental",
    "Time treated post induction (min)": "5",
    "Compound identifier": "TC39",
    "TCAMS identifier": "TCMDC-123880",
    "ChEMBL identifier": "CHEMBL588378",
    "Compound linkout": "https://www.ebi.ac.uk/chembl/compound_report_card/CHEMBL588378/",
    "Concentration (uM)": "10"
  }
}