{
  "id": "9ef94b5c-061c-4e60-a095-600d5920cc71",
  "accession_id": "S-BIAD633",
  "name": "Primary_Screen/Individual_cells/Sequence_ 200207 CPD7 T20 0010-MaxIP.nd2 (series 1)_crop1 - 146 x 133 x 1 x 1 - 2 ch (16 bits).tif",
  "original_relpath": "Primary_Screen/Individual_cells/Sequence_ 200207 CPD7 T20 0010-MaxIP.nd2 (series 1)_crop1 - 146 x 133 x 1 x 1 - 2 ch (16 bits).tif",
  "dimensions": null,
  "representations": [
    {
      "accession_id": "S-BIAD633",
      "image_id": "9ef94b5c-061c-4e60-a095-600d5920cc71",
      "uri": "https://ftp.ebi.ac.uk/biostudies/fire/S-BIAD/633/S-BIAD633/Files/Primary_Screen/Individual_cells/Sequence_ 200207 CPD7 T20 0010-MaxIP.nd2 (series 1)_crop1 - 146 x 133 x 1 x 1 - 2 ch (16 bits).tif",
      "size": 93104,
      "type": "fire_object",
      "dimensions": null,
      "attributes": {
        "fileref_ids": [
          "d30037e8-13dd-4f02-82d6-354ee34b1649"
        ]
      },
      "rendering": null
    }
  ],
  "attributes": {
    "Filetype": "ISOLATED_CELL",
    "Experiment ID": "primary_screen",
    "Assay Type": "24h preincubation",
    "Sample Type": "Experimental",
    "Compound identifier": "DDD01035881",
    "TCAMS identifier": "NA",
    "ChEMBL identifier": "CHEMBL3444189",
    "Compound linkout": "https://www.ebi.ac.uk/chembl/compound_report_card/CHEMBL3444189/",
    "Concentration (uM)": "10"
  }
}