{
  "id": "bd40e697-b1ba-42dd-8414-39bb332684fb",
  "accession_id": "S-BIAD633",
  "name": "Timecourses/Individual_cells/Sequence_ VB T15 06.nd2 (channels 0 1)_crop2 - 128 x 143 x 1 x 1 - 2 ch (double).tif",
  "original_relpath": "Timecourses/Individual_cells/Sequence_ VB T15 06.nd2 (channels 0 1)_crop2 - 128 x 143 x 1 x 1 - 2 ch (double).tif",
  "dimensions": null,
  "representations": [
    {
      "accession_id": "S-BIAD633",
      "image_id": "bd40e697-b1ba-42dd-8414-39bb332684fb",
      "uri": "https://ftp.ebi.ac.uk/biostudies/fire/S-BIAD/633/S-BIAD633/Files/Timecourses/Individual_cells/Sequence_ VB T15 06.nd2 (channels 0 1)_crop2 - 128 x 143 x 1 x 1 - 2 ch (double).tif",
      "size": 124717,
      "type": "fire_object",
      "dimensions": null,
      "attributes": {
        "fileref_ids": [
          "79f5d0d9-d2d0-447a-863b-ba00d31d257f"
        ]
      },
      "rendering": null
    }
  ],
  "attributes": {
    "Filetype": "ISOLATED_CELL",
    "Experiment ID": "TIME_VB_39",
    "Assay Type": "Gametogenesis_timecourse",
    "Sample type": "Experimental",
    "Time treated post induction (min)": "15",
    "Compound identifier": "Vinblastine",
    "TCAMS identifier": "NA",
    "ChEMBL identifier": "CHEMBL159",
    "Compound linkout": "https://www.ebi.ac.uk/chembl/compound_report_card/CHEMBL159/",
    "Concentration (uM)": "1"
  }
}