{
  "id": "cf34cbea-8e71-4589-8d6a-73726c6e4388",
  "accession_id": "S-BIAD633",
  "name": "Timecourses/Masked/Sequence_ TC16 T0 019 - Deconvolved, Type Automatic-MaxIP.nd2 - 2048 x 2044 x 1 x 1 - 2 ch (double).tif",
  "original_relpath": "Timecourses/Masked/Sequence_ TC16 T0 019 - Deconvolved, Type Automatic-MaxIP.nd2 - 2048 x 2044 x 1 x 1 - 2 ch (double).tif",
  "dimensions": null,
  "representations": [
    {
      "accession_id": "S-BIAD633",
      "image_id": "cf34cbea-8e71-4589-8d6a-73726c6e4388",
      "uri": "https://ftp.ebi.ac.uk/biostudies/fire/S-BIAD/633/S-BIAD633/Files/Timecourses/Masked/Sequence_ TC16 T0 019 - Deconvolved, Type Automatic-MaxIP.nd2 - 2048 x 2044 x 1 x 1 - 2 ch (double).tif",
      "size": 17247773,
      "type": "fire_object",
      "dimensions": null,
      "attributes": {
        "fileref_ids": [
          "3c301ecd-c499-4e77-9cf1-3348b1fa2cf1"
        ]
      },
      "rendering": null
    }
  ],
  "attributes": {
    "Filetype": "BACK_COR_Image",
    "Experiment ID": "TIME_11_14_16",
    "Assay Type": "Gametogenesis_timecourse",
    "Sample type": "Experimental",
    "Time treated post induction (min)": "0",
    "Compound identifier": "TC16",
    "TCAMS identifier": "TCMDC-141382",
    "ChEMBL identifier": "CHEMBL535088",
    "Compound linkout": "https://www.ebi.ac.uk/chembl/compound_report_card/CHEMBL535088/",
    "Concentration (uM)": "12"
  }
}