{
  "id": "cfba84c2-1ad5-4016-b14c-454ce27e114d",
  "accession_id": "S-BIAD633",
  "name": "Timecourses/Individual_cells/Sequence_ VB T00 01.nd2 (channels 0 1)_crop1 - 138 x 193 x 1 x 1 - 2 ch (double).tif",
  "original_relpath": "Timecourses/Individual_cells/Sequence_ VB T00 01.nd2 (channels 0 1)_crop1 - 138 x 193 x 1 x 1 - 2 ch (double).tif",
  "dimensions": null,
  "representations": [
    {
      "accession_id": "S-BIAD633",
      "image_id": "cfba84c2-1ad5-4016-b14c-454ce27e114d",
      "uri": "https://ftp.ebi.ac.uk/biostudies/fire/S-BIAD/633/S-BIAD633/Files/Timecourses/Individual_cells/Sequence_ VB T00 01.nd2 (channels 0 1)_crop1 - 138 x 193 x 1 x 1 - 2 ch (double).tif",
      "size": 190989,
      "type": "fire_object",
      "dimensions": null,
      "attributes": {
        "fileref_ids": [
          "f49270d6-0bbd-415a-8fde-3c85f02e808f"
        ]
      },
      "rendering": null
    }
  ],
  "attributes": {
    "Filetype": "ISOLATED_CELL",
    "Experiment ID": "TIME_VB_39",
    "Assay Type": "Gametogenesis_timecourse",
    "Sample type": "Experimental",
    "Time treated post induction (min)": "0",
    "Compound identifier": "Vinblastine",
    "TCAMS identifier": "NA",
    "ChEMBL identifier": "CHEMBL159",
    "Compound linkout": "https://www.ebi.ac.uk/chembl/compound_report_card/CHEMBL159/",
    "Concentration (uM)": "1"
  }
}