{
  "id": "eb298d0c-12c4-4287-a1e2-eb88e009c694",
  "accession_id": "S-BIAD633",
  "name": "Primary_Screen/Individual_cells/Sequence_ 200130 DMSO T0013-MaxIP.nd2 (series 1)_crop1 - 102 x 263 x 1 x 1 - 2 ch (16 bits).tif",
  "original_relpath": "Primary_Screen/Individual_cells/Sequence_ 200130 DMSO T0013-MaxIP.nd2 (series 1)_crop1 - 102 x 263 x 1 x 1 - 2 ch (16 bits).tif",
  "dimensions": null,
  "representations": [
    {
      "accession_id": "S-BIAD633",
      "image_id": "eb298d0c-12c4-4287-a1e2-eb88e009c694",
      "uri": "https://ftp.ebi.ac.uk/biostudies/fire/S-BIAD/633/S-BIAD633/Files/Primary_Screen/Individual_cells/Sequence_ 200130 DMSO T0013-MaxIP.nd2 (series 1)_crop1 - 102 x 263 x 1 x 1 - 2 ch (16 bits).tif",
      "size": 121108,
      "type": "fire_object",
      "dimensions": null,
      "attributes": {
        "fileref_ids": [
          "a5d7d4a5-68b7-458b-85b6-2d26fb2edd99"
        ]
      },
      "rendering": null
    }
  ],
  "attributes": {
    "Filetype": "ISOLATED_CELL",
    "Experiment ID": "primary_screen",
    "Assay Type": "24h preincubation",
    "Sample Type": "Unactivated DMSO control",
    "Compound identifier": "NA",
    "TCAMS identifier": "NA",
    "ChEMBL identifier": "NA",
    "Compound linkout": "NA",
    "Concentration (uM)": "NA"
  }
}