{
  "id": "881a57a6-6da1-4306-bd8b-db0da2c8a076",
  "accession_id": "S-BIAD867",
  "name": "idr0004/P130.ome.zarr.zip",
  "original_relpath": "idr0004/P130.ome.zarr.zip",
  "dimensions": null,
  "representations": [
    {
      "accession_id": "S-BIAD867",
      "image_id": "881a57a6-6da1-4306-bd8b-db0da2c8a076",
      "uri": "https://ftp.ebi.ac.uk/biostudies/fire/S-BIAD/867/S-BIAD867/Files/idr0004/P130.ome.zarr.zip",
      "size": 301628790,
      "type": "zipped_zarr",
      "dimensions": null,
      "attributes": {
        "fileref_ids": [
          "6229133c-b627-4f60-b8f7-1a24bf5e4d8e"
        ],
        "path_in_zarr": "/0"
      },
      "rendering": null
    }
  ],
  "attributes": {}
}