{
  "id": "746ef5d2-7253-4c41-8ee0-f01d5efabfec",
  "accession_id": "S-BIAD463",
  "name": "my_submission/Training_coco/IDC with metastasis/Pilot cohort/Patient_038/3.png",
  "original_relpath": "my_submission/Training_coco/IDC with metastasis/Pilot cohort/Patient_038/3.png",
  "dimensions": null,
  "representations": [
    {
      "accession_id": "S-BIAD463",
      "image_id": "746ef5d2-7253-4c41-8ee0-f01d5efabfec",
      "uri": "https://ftp.ebi.ac.uk/biostudies/fire/S-BIAD/463/S-BIAD463/Files/my_submission/Training_coco/IDC with metastasis/Pilot cohort/Patient_038/3.png",
      "size": 2276654,
      "type": "fire_object",
      "dimensions": null,
      "attributes": {
        "fileref_ids": [
          "b898b86a-a234-42be-842e-ce42bf1eeaab"
        ]
      },
      "rendering": null
    }
  ],
  "attributes": {
    "Description": "RGB image (see my_submission/Training_coco/COCO_annotations.json for list of annotations)"
  }
}