{
  "id": "eb994072-de07-4e52-9d93-9830d30ba760",
  "accession_id": "S-BIAD463",
  "name": "my_submission/Training_coco/IDC without metastasis/Patient_052/33.png",
  "original_relpath": "my_submission/Training_coco/IDC without metastasis/Patient_052/33.png",
  "dimensions": null,
  "representations": [
    {
      "accession_id": "S-BIAD463",
      "image_id": "eb994072-de07-4e52-9d93-9830d30ba760",
      "uri": "https://ftp.ebi.ac.uk/biostudies/fire/S-BIAD/463/S-BIAD463/Files/my_submission/Training_coco/IDC without metastasis/Patient_052/33.png",
      "size": 2457590,
      "type": "fire_object",
      "dimensions": null,
      "attributes": {
        "fileref_ids": [
          "22c317c5-b29c-4608-a770-04ca02b8fc69"
        ]
      },
      "rendering": null
    }
  ],
  "attributes": {
    "Description": "RGB image (see my_submission/Training_coco/COCO_annotations.json for list of annotations)"
  }
}