{
  "id": "9ad086c5-8e9f-4fda-aedb-3dd32e4dc470",
  "accession_id": "S-BSST999",
  "name": "Soure data of microscopy/Figure 5/5B/GS/HC4-1.tif",
  "original_relpath": "Soure data of microscopy/Figure 5/5B/GS/HC4-1.tif",
  "dimensions": null,
  "representations": [
    {
      "accession_id": "S-BSST999",
      "image_id": "9ad086c5-8e9f-4fda-aedb-3dd32e4dc470",
      "uri": "https://ftp.ebi.ac.uk/biostudies/fire/S-BSST/999/S-BSST999/Files/Soure data of microscopy.zip",
      "size": 4211682,
      "type": "fire_object",
      "dimensions": null,
      "attributes": {
        "fileref_ids": [
          "411ad5a1-75c1-476b-8227-60f69e7efbcb"
        ]
      },
      "rendering": null
    }
  ],
  "attributes": {
    "Description": "Raw data of Fig5B,5D, EV2B, EV4B, EV5E, and EV5H",
    "Type": "tif or lsm"
  }
}